netconf_parser/__init__.py
netconf_parser/compare.py
netconf_parser/models.py
netconf_parser/parser.py
netconf_parser/search.py
netconf_parser-1.1.0.dist-info/licenses/LICENSE
netconf_parser-1.1.0.dist-info/METADATA
netconf_parser-1.1.0.dist-info/WHEEL
netconf_parser-1.1.0.dist-info/top_level.txt
netconf_parser-1.1.0.dist-info/RECORD
