Metadata-Version: 2.4
Name: netconf-parser
Version: 1.1.0
Summary: A Python library for parsing and comparing hierarchical network device configurations
Author-email: Hamza Bouabdallah <w4hf@pm.me>
Maintainer-email: Hamza Bouabdallah <w4hf@pm.me>
License: MIT
Project-URL: Homepage, https://github.com/w4hf/netconf-parser
Project-URL: Documentation, https://github.com/w4hf/netconf-parser#readme
Project-URL: Repository, https://github.com/w4hf/netconf-parser
Project-URL: Issues, https://github.com/w4hf/netconf-parser/issues
Project-URL: Changelog, https://github.com/w4hf/netconf-parser/releases
Keywords: network,configuration,parser,netconf,cisco,juniper,diff,compare
Classifier: Development Status :: 4 - Beta
Classifier: Intended Audience :: Developers
Classifier: Intended Audience :: System Administrators
Classifier: Intended Audience :: Telecommunications Industry
Classifier: License :: OSI Approved :: MIT License
Classifier: Programming Language :: Python :: 3
Classifier: Programming Language :: Python :: 3.12
Classifier: Programming Language :: Python :: 3.13
Classifier: Topic :: Software Development :: Libraries :: Python Modules
Classifier: Topic :: System :: Networking
Classifier: Topic :: System :: Systems Administration
Classifier: Operating System :: OS Independent
Requires-Python: >=3.12
License-File: LICENSE
Provides-Extra: dev
Requires-Dist: pytest>=8.0.0; extra == "dev"
Requires-Dist: pytest-cov>=4.1.0; extra == "dev"
Dynamic: license-file
